targomiko/__init__.py
targomiko/command.py
targomiko/connection.py
targomiko-0.2.0.dist-info/LICENSE
targomiko-0.2.0.dist-info/METADATA
targomiko-0.2.0.dist-info/WHEEL
targomiko-0.2.0.dist-info/top_level.txt
targomiko-0.2.0.dist-info/RECORD
