Metadata-Version: 2.1
Name: targomiko
Version: 0.2.0
Summary: My package description
Home-page: https://github.com/targodan/targomiko
Author: Luca Corbatto
Author-email: luca@corbatto.de
License: MIT
Keywords: one,two
Platform: UNKNOWN
License-File: LICENSE
Requires-Dist: wheel
